OxySDK.py
_OxySDK.cp310-win_amd64.pyd
_speechy.cp310-win_amd64.pyd
speechy.py
speechy-1.0.7.dist-info/METADATA
speechy-1.0.7.dist-info/WHEEL
speechy-1.0.7.dist-info/top_level.txt
speechy-1.0.7.dist-info/RECORD
