Metadata-Version: 2.1
Name: speechy
Version: 1.0.7
Summary: Speechy Python SDK
Home-page: UNKNOWN
Author: Speechy
Author-email: support@oxycom.co.uk
License: License :: Other/Proprietary License
Platform: UNKNOWN
